COPYING.txt
MANIFEST.in
README.txt
setup.py
PyNFG.egg-info/PKG-INFO
PyNFG.egg-info/SOURCES.txt
PyNFG.egg-info/dependency_links.txt
PyNFG.egg-info/requires.txt
PyNFG.egg-info/top_level.txt
bin/hideandseek.py
bin/stackelberg.py
docs/_build/html/genindex.html
docs/_build/html/index.html
docs/_build/html/py-modindex.html
docs/_build/html/pynfg.chancenode.html
docs/_build/html/pynfg.decisionnode.html
docs/_build/html/pynfg.deternode.html
docs/_build/html/pynfg.gameclasses.html
docs/_build/html/pynfg.iq_coordinated.html
docs/_build/html/pynfg.iq_iterated.html
docs/_build/html/pynfg.iq_policy.html
docs/_build/html/pynfg.iq_uncoordinated.html
docs/_build/html/pynfg.iterseminfg.html
docs/_build/html/pynfg.mcrl.html
docs/_build/html/pynfg.node.html
docs/_build/html/pynfg.nodeclasses.html
docs/_build/html/pynfg.pgtsolutions.html
docs/_build/html/pynfg.qlearning.html
docs/_build/html/pynfg.rlsolutions.html
docs/_build/html/pynfg.seminfg.html
docs/_build/html/pynfg.utilities.html
docs/_build/html/search.html
docs/_build/html/searchindex.js
docs/_build/html/_modules/index.html
docs/_build/html/_modules/pynfg/classes/chancenode.html
docs/_build/html/_modules/pynfg/classes/decisionnode.html
docs/_build/html/_modules/pynfg/classes/deternode.html
docs/_build/html/_modules/pynfg/classes/iterseminfg.html
docs/_build/html/_modules/pynfg/classes/node.html
docs/_build/html/_modules/pynfg/classes/seminfg.html
docs/_build/html/_modules/pynfg/pgtsolutions/intelligence/coordinated.html
docs/_build/html/_modules/pynfg/pgtsolutions/intelligence/iterated.html
docs/_build/html/_modules/pynfg/pgtsolutions/intelligence/policy.html
docs/_build/html/_modules/pynfg/pgtsolutions/intelligence/uncoordinated.html
docs/_build/html/_modules/pynfg/rlsolutions/mcrl.html
docs/_build/html/_modules/pynfg/rlsolutions/qlearning.html
docs/_build/html/_modules/pynfg/utilities/utilities.html
docs/_build/html/_static/ajax-loader.gif
docs/_build/html/_static/basic.css
docs/_build/html/_static/comment-bright.png
docs/_build/html/_static/comment-close.png
docs/_build/html/_static/comment.png
docs/_build/html/_static/default.css
